fpythonic/__init__.py
fpythonic/py.typed
fpythonic-1.4.0.dist-info/licenses/LICENSE
fpythonic-1.4.0.dist-info/WHEEL
fpythonic-1.4.0.dist-info/METADATA
fpythonic-1.4.0.dist-info/RECORD
