Metadata-Version: 2.4
Name: fpythonic
Version: 1.4.0
Summary: Pythonic Functional Programming  -  PyPI `fpypthonic` Namespace packages
Author-email: "Geoffrey R. Scheller" <geoffrey@scheller.com>
Requires-Python: >=3.12
Classifier: Development Status :: 5 - Production/Stable
Classifier: Framework :: Pytest
Classifier: Intended Audience :: Developers
Classifier: License :: OSI Approved :: Apache Software License
Classifier: Operating System :: OS Independent
Classifier: Programming Language :: Python :: 3.13
Classifier: Typing :: Typed
License-File: LICENSE
Project-URL: Changelog, https://github.com/grscheller/fpythonic/blob/main/CHANGELOG.md
Project-URL: Documentation, https://grscheller.github.io/fpythonic
Project-URL: Homepage, https://github.com/grscheller/fpythonic/blob/main/README.md
Project-URL: Source, https://github.com/grscheller/fpythonic
